stacn/__init__.py
stacn/cluster.py
stacn/enhence.py
stacn/load_data.py
stacn/logger.py
stacn/networks.py
stacn/st_acn.py
stacn/utils.py
stACN-1.0.2.dist-info/LICENSE
stACN-1.0.2.dist-info/METADATA
stACN-1.0.2.dist-info/WHEEL
stACN-1.0.2.dist-info/top_level.txt
stACN-1.0.2.dist-info/RECORD
