Metadata-Version: 2.1
Name: stACN
Version: 1.0.2
Summary: The initial package of stACN
Author-email: Haiyue Wang <haiyue_wang1223@163.com>
Project-URL: Homepage, https://github.com/xkmaxidian/stACN
Project-URL: Issues, https://github.com/xkmaxidian/stACN/issues
Classifier: Programming Language :: Python :: 3
Classifier: License :: OSI Approved :: MIT License
Classifier: Operating System :: OS Independent
Requires-Python: >=3.8
License-File: LICENSE
Requires-Dist: scanpy >=1.9.3
Requires-Dist: numpy >=1.26.4
Requires-Dist: pandas >=2.2.1
Requires-Dist: anndata >=0.10.7
Requires-Dist: matplotlib >=3.8.4
Requires-Dist: scipy >=1.13.0
Requires-Dist: scikit-learn >=1.4.2
Requires-Dist: psutil >=5.9.0
Requires-Dist: tqdm >=4.66.4
Requires-Dist: leidenalg >=0.10.1
Requires-Dist: torch >=2.0.1
Requires-Dist: mnmstpy >=1.1.0
Requires-Dist: torchvision >=0.15.2
Requires-Dist: natsort >=7.1.1
Requires-Dist: igraph >=0.11.2
